StringToInteger/StrToInt.py
StringToInteger/__init__.py
StringToInteger-1.0.1.dist-info/METADATA
StringToInteger-1.0.1.dist-info/WHEEL
StringToInteger-1.0.1.dist-info/top_level.txt
StringToInteger-1.0.1.dist-info/RECORD
