Metadata-Version: 2.1
Name: StringToInteger
Version: 1.0.1
Summary: Convert your string to integer
Home-page: https://github.com/mytja/String-to-Integer-for-Python
Author: MyTja Team
Author-email: mamnju21@gmail.com
License: UNKNOWN
Platform: UNKNOWN
Classifier: Programming Language :: Python :: 3
Classifier: License :: OSI Approved :: MIT License
Classifier: Operating System :: OS Independent
Requires-Python: >=2.3,!=3.0.*,!=3.1.*,!=3.2.*,!=3.3.*
